exponea_python_sdk/__init__.py
exponea_python_sdk/analyses.py
exponea_python_sdk/catalog.py
exponea_python_sdk/client.py
exponea_python_sdk/customer.py
exponea_python_sdk/exceptions.py
exponea_python_sdk/tracking.py
exponea_python_sdk-0.2.0.dist-info/LICENSE
exponea_python_sdk-0.2.0.dist-info/METADATA
exponea_python_sdk-0.2.0.dist-info/WHEEL
exponea_python_sdk-0.2.0.dist-info/top_level.txt
exponea_python_sdk-0.2.0.dist-info/RECORD
