Metadata-Version: 2.1
Name: exponea-python-sdk
Version: 0.2.0
Summary: A Python client for Exponea Data API
Home-page: https://github.com/exponea/exponea-python-sdk
Author: Exponea
Author-email: info@exponea.com
License: UNKNOWN
Platform: UNKNOWN
Classifier: Programming Language :: Python :: 3
Classifier: License :: OSI Approved :: MIT License
Classifier: Operating System :: OS Independent
